pathsingle/__init__.py
pathsingle/activity.py
pathsingle/bench_challenge.ipynb
pathsingle/bench_pbmc.ipynb
pathsingle/bench_pbmc_shap.ipynb
pathsingle/bench_seurat.ipynb
pathsingle/benchmark.md
pathsingle/benchmark.py
pathsingle/feature_reduction.ipynb
pathsingle/learn_atom.ipynb
pathsingle/learn_mlxtend.ipynb
pathsingle/metrics.py
pathsingle/seurat.R
pathsingle/__pycache__/.gitignore
pathsingle/__pycache__/activity.cpython-39.pyc
pathsingle/__pycache__/metrics.cpython-39.pyc
pathsingle/__pycache__/udp.cpython-39.pyc
pathsingle/data/Pathsingle.png
pathsingle/data/__init__.py
pathsingle/data/adata_pbmc.h5ad
pathsingle/data/c2.cp.reactome.v7.5.1.symbols.gmt
pathsingle/data/gsea_results_matrix.npy
pathsingle/data/pathway_relations.csv
pathsingle/data/pbmc3k_filtered_gene_bc_matrices.tar.gz
pathsingle/data/sample_file.csv
pathsingle/data/seurat_clusters.csv
pathsingle/data/hg19b/barcodes.tsv
pathsingle/data/hg19b/genes.tsv
pathsingle/data/hg19b/matrix.mtx
pathsingle/pathway_db/__init__.py
pathsingle/pathway_db/download_kegg.py
pathsingle/pathway_db/gene2symbol.csv
pathsingle/pathway_db/kegg_pathways.csv
pathsingle/pathway_db/kgml2sif2.py
pathsingle/pathway_db/kgml_files.zip
pathsingle-0.2.0.dist-info/LICENSE
pathsingle-0.2.0.dist-info/METADATA
pathsingle-0.2.0.dist-info/WHEEL
pathsingle-0.2.0.dist-info/top_level.txt
pathsingle-0.2.0.dist-info/RECORD
