Metadata-Version: 2.1
Name: pathsingle
Version: 0.2.0
Summary: PathSingle is a Python package for pathway analysis of single-cell RNA-seq data.
Home-page: https://github.com/zurkin1/pathsingle
Author: Dani Livne
Author-email: zurkin@gmail.com
License: MIT
Platform: UNKNOWN
Classifier: Development Status :: 3 - Alpha
Classifier: Intended Audience :: Developers
Classifier: License :: OSI Approved :: MIT License
Classifier: Programming Language :: Python :: 3
Classifier: Programming Language :: Python :: 3.6
Classifier: Programming Language :: Python :: 3.7
Classifier: Programming Language :: Python :: 3.8
Classifier: Programming Language :: Python :: 3.9
Classifier: Programming Language :: Python :: 3.10
Classifier: Programming Language :: Python :: 3.11
Classifier: Programming Language :: Python :: 3.12
Requires-Python: >=3.6
License-File: LICENSE
Requires-Dist: numpy
Requires-Dist: scipy
Requires-Dist: pandas
Requires-Dist: scikit-learn
Requires-Dist: scanpy
Requires-Dist: tqdm
Requires-Dist: omnipath
Requires-Dist: umap-learn
Requires-Dist: magic-impute
Requires-Dist: matplotlib
Requires-Dist: scprep
Requires-Dist: seaborn
